eyec.py
eyec-0.1.0.dist-info/METADATA
eyec-0.1.0.dist-info/WHEEL
eyec-0.1.0.dist-info/entry_points.txt
eyec-0.1.0.dist-info/top_level.txt
eyec-0.1.0.dist-info/RECORD
