Metadata-Version: 2.4
Name: eyec
Version: 0.1.0
Summary: A simple clipboard history + search tool for Linux
Author: Your Name
License: MIT
Classifier: Programming Language :: Python :: 3
Classifier: Operating System :: POSIX :: Linux
Requires-Dist: pyperclip
Dynamic: author
Dynamic: classifier
Dynamic: description
Dynamic: description-content-type
Dynamic: license
Dynamic: requires-dist
Dynamic: summary
